jieting_tool_package/__init__.py
jieting_tool_package/tools/__init__.py
jieting_tool_package/tools/my_tool_1.py
jieting_tool_package/tools/my_tool_2.py
jieting_tool_package/tools/utils.py
jieting_tool_package/yamls/jieting_tool_1.yaml
jieting_tool_package/yamls/my_tool_2.yaml
my_tool_package/__init__.py
my_tool_package/tools/__init__.py
my_tool_package/tools/my_tool_1.py
my_tool_package/tools/my_tool_2.py
my_tool_package/tools/utils.py
my_tool_package/yamls/my_tool_1.yaml
my_tool_package/yamls/my_tool_2.yaml
tests/__init__.py
tests/test_my_tool_1.py
tests/test_my_tool_2.py
jieting_tool_package-0.0.1.dist-info/METADATA
jieting_tool_package-0.0.1.dist-info/WHEEL
jieting_tool_package-0.0.1.dist-info/entry_points.txt
jieting_tool_package-0.0.1.dist-info/top_level.txt
jieting_tool_package-0.0.1.dist-info/RECORD
